README.md
setup.py
noc_rest_api_client.egg-info/PKG-INFO
noc_rest_api_client.egg-info/SOURCES.txt
noc_rest_api_client.egg-info/dependency_links.txt
noc_rest_api_client.egg-info/requires.txt
noc_rest_api_client.egg-info/top_level.txt
swagger_client/__init__.py
swagger_client/api_client.py
swagger_client/configuration.py
swagger_client/rest.py
swagger_client/api/__init__.py
swagger_client/api/accumulated_values_api.py
swagger_client/api/aircraft_api.py
swagger_client/api/airport_api.py
swagger_client/api/com_channel_api.py
swagger_client/api/configuration_data_api.py
swagger_client/api/configuration_management_api.py
swagger_client/api/crew_api.py
swagger_client/api/flight_api.py
swagger_client/api/hotel_api.py
swagger_client/api/human_resource_api.py
swagger_client/api/maintenance_api.py
swagger_client/api/pairing_api.py
swagger_client/api/roster_api.py
swagger_client/api/schedule_api.py
swagger_client/api/turn_around_rule_api.py
swagger_client/api/user_api.py
swagger_client/models/__init__.py
swagger_client/models/accumulated_value.py
swagger_client/models/accumulated_value_label.py
swagger_client/models/address.py
swagger_client/models/aircraft.py
swagger_client/models/aircraft_in.py
swagger_client/models/aircraft_instance.py
swagger_client/models/aircraft_note_dto.py
swagger_client/models/aircraft_type.py
swagger_client/models/airport.py
swagger_client/models/airport_data.py
swagger_client/models/airport_distance_data.py
swagger_client/models/airports.py
swagger_client/models/assigned_crew.py
swagger_client/models/atc_edct_out.py
swagger_client/models/automation_event_out.py
swagger_client/models/base.py
swagger_client/models/bases_info.py
swagger_client/models/booking_data.py
swagger_client/models/com_channel.py
swagger_client/models/company.py
swagger_client/models/complement_description.py
swagger_client/models/contract.py
swagger_client/models/contracts_data.py
swagger_client/models/crew.py
swagger_client/models/crew_complement.py
swagger_client/models/crew_complement_detail.py
swagger_client/models/crew_in.py
swagger_client/models/crew_on_board.py
swagger_client/models/crew_on_board_info.py
swagger_client/models/crew_type.py
