Metadata-Version: 2.1
Name: noc-rest-api-client
Version: 1.0.0
Summary: RESTful.Service
Home-page: 
Author-email: 
Keywords: Swagger,RESTful.Service
